Xclusion_criteria/__init__.py
Xclusion_criteria/xclusion.py
Xclusion_criteria/xclusion_alt.py
Xclusion_criteria/xclusion_crits.py
Xclusion_criteria/xclusion_dtypes.py
Xclusion_criteria/xclusion_io.py
Xclusion_criteria/xclusion_plot.py
Xclusion_criteria/resources/nulls.txt
Xclusion_criteria/resources/template.chart.json
Xclusion_criteria/resources/template.text.html
Xclusion_criteria/scripts/__init__.py
Xclusion_criteria/scripts/_standalone_xclusion.py
Xclusion_criteria/tests/__init__.py
Xclusion_criteria/tests/test_xclusion_crits.py
Xclusion_criteria/tests/test_xclusion_dtypes.py
Xclusion_criteria/tests/test_xclusion_io.py
Xclusion_criteria-0.2.0.dist-info/LICENSE
Xclusion_criteria-0.2.0.dist-info/METADATA
Xclusion_criteria-0.2.0.dist-info/WHEEL
Xclusion_criteria-0.2.0.dist-info/entry_points.txt
Xclusion_criteria-0.2.0.dist-info/top_level.txt
Xclusion_criteria-0.2.0.dist-info/RECORD
