Metadata-Version: 2.1
Name: Xclusion-criteria
Version: 0.2.0
Summary: Generate interactive, user-defined visualisations to helpdefining inclusion/exclusion criteria on a metadata table.
Home-page: https://github.com/FranckLejzerowicz/Xclusion_criteria
Author: Franck Lejzerowicz
Author-email: franck.lejzerowicz@gmail.com
Maintainer: Franck Lejzerowicz
Maintainer-email: franck.lejzerowicz@gmail.com
License: BSD
Classifier: License :: OSI Approved :: BSD License
Classifier: Topic :: Scientific/Engineering
Classifier: Topic :: Scientific/Engineering :: Bio-Informatics
Classifier: Programming Language :: Python :: 3.6
Classifier: Programming Language :: Python :: 3 :: Only
Classifier: Operating System :: Unix
Classifier: Operating System :: POSIX
Classifier: Operating System :: MacOS :: MacOS X
Requires-Python: >=3.6
License-File: LICENSE
Requires-Dist: click (>=6.7)
Requires-Dist: numpy (>=1.18.1)
Requires-Dist: pandas (>=1.0.1)
Requires-Dist: altair (>=3.2.0)
Requires-Dist: cython (>=0.29.15)
Requires-Dist: biom-format (>=2.1.5)
Requires-Dist: redbiom (>=0.3.5)
Requires-Dist: matplotlib
Requires-Dist: pyyaml
